spbessax/__init__.py
spbessax/coefficients.py
spbessax/functions.py
spbessax/roots.py
spbessax-0.1.3.dist-info/AUTHORS
spbessax-0.1.3.dist-info/LICENSE
spbessax-0.1.3.dist-info/METADATA
spbessax-0.1.3.dist-info/NOTICE
spbessax-0.1.3.dist-info/WHEEL
spbessax-0.1.3.dist-info/top_level.txt
spbessax-0.1.3.dist-info/RECORD
