Metadata-Version: 2.1
Name: spbessax
Version: 0.1.3
Summary: spherical Bessel functions for JAX
Keywords: Spherical Bessel functions,Bessel,JAX
Requires-Python: >=3.7
License-File: LICENSE
License-File: NOTICE
License-File: AUTHORS
Requires-Dist: jax
Requires-Dist: numpy
Provides-Extra: dev
Requires-Dist: pytest; extra == "dev"
Requires-Dist: scipy; extra == "dev"
Requires-Dist: matplotlib; extra == "dev"
